anthroab/__init__.py
anthroab/__version__.py
anthroab/cli.py
anthroab/predict.py
anthroab-1.1.0.dist-info/licenses/LICENSE
anthroab-1.1.0.dist-info/METADATA
anthroab-1.1.0.dist-info/WHEEL
anthroab-1.1.0.dist-info/entry_points.txt
anthroab-1.1.0.dist-info/top_level.txt
anthroab-1.1.0.dist-info/RECORD
