Metadata-Version: 2.4
Name: anthroab
Version: 1.1.0
Summary: AnthroAb: Human antibody language model based on RoBERTa for humanization
Home-page: https://github.com/nagarh/AnthroAb
Author: Hemant Nagar
Author-email: hn533621@ohio.edu
License: MIT
Project-URL: Bug Reports, https://github.com/nagarh/AnthroAb/issues
Project-URL: Source, https://github.com/nagarh/AnthroAb
Project-URL: Documentation, https://github.com/nagarh/AnthroAb
Project-URL: Download, https://github.com/nagarh/AnthroAb/releases
Keywords: anthroab,antibody humanization,roberta,biophi,antibody design,bioinformatics,protein engineering
Classifier: Development Status :: 4 - Beta
Classifier: Intended Audience :: Science/Research
Classifier: Programming Language :: Python :: 3
Classifier: Programming Language :: Python :: 3.10
Classifier: Programming Language :: Python :: 3.11
Classifier: Programming Language :: Python :: 3.12
Classifier: Topic :: Scientific/Engineering :: Bio-Informatics
Classifier: Topic :: Scientific/Engineering :: Artificial Intelligence
Classifier: Topic :: Software Development :: Libraries :: Python Modules
Requires-Python: >=3.10
License-File: LICENSE
Requires-Dist: pandas>=1.0.0
Requires-Dist: transformers>=4.0.0
Requires-Dist: torch>=1.7.0
Requires-Dist: numpy>=1.19.0
Requires-Dist: tqdm>=4.0.0
Dynamic: author
Dynamic: author-email
Dynamic: classifier
Dynamic: description
Dynamic: description-content-type
Dynamic: home-page
Dynamic: keywords
Dynamic: license
Dynamic: license-file
Dynamic: project-url
Dynamic: requires-dist
Dynamic: requires-python
Dynamic: summary
